cmem_plugin_pgvector/__init__.py
cmem_plugin_pgvector/commons.py
cmem_plugin_pgvector/postgresql.svg
cmem_plugin_pgvector/search_task.py
cmem_plugin_pgvector/store_task.py
cmem_plugin_pgvector-0.9.0.dist-info/METADATA
cmem_plugin_pgvector-0.9.0.dist-info/WHEEL
cmem_plugin_pgvector-0.9.0.dist-info/licenses/LICENSE
cmem_plugin_pgvector-0.9.0.dist-info/RECORD
