Metadata-Version: 2.4
Name: cmem-plugin-pgvector
Version: 0.9.0
Summary: Store and search for embedding vectors in a Postgres vector store.
License: Apache-2.0
License-File: LICENSE
Keywords: eccenca Corporate Memory,plugin
Author: eccenca GmbH
Author-email: cmempy-developer@eccenca.com
Maintainer: Edgard Marx
Maintainer-email: edgard.marx@eccenca.com
Requires-Python: >=3.13,<4.0
Classifier: Development Status :: 4 - Beta
Classifier: Environment :: Plugins
Classifier: License :: OSI Approved :: Apache Software License
Classifier: Programming Language :: Python :: 3
Classifier: Programming Language :: Python :: 3.13
Classifier: Programming Language :: Python :: 3.14
Requires-Dist: cmem-plugin-base (>=4.15.0,<5.0.0)
Requires-Dist: langchain-core (>=0.3.71,<0.4.0)
Requires-Dist: langchain-postgres (>=0.0.15,<0.0.16)
Requires-Dist: psycopg[binary] (>=3.2.9,<4.0.0)
